xemeler/__init__.py
xemeler-0.0.1b0.dist-info/LICENSE
xemeler-0.0.1b0.dist-info/METADATA
xemeler-0.0.1b0.dist-info/WHEEL
xemeler-0.0.1b0.dist-info/top_level.txt
xemeler-0.0.1b0.dist-info/RECORD
