Metadata-Version: 2.1
Name: xemeler
Version: 0.0.1b0
Summary: The best way to work with XML in Python.
Home-page: https://github.com/ispaneli/xemeler
Author: Ilya Antonov
Author-email: ispanelki@gmail.com
Project-URL: Issue Tracker, https://github.com/ispaneli/xemeler/issues
Project-URL: Source, https://github.com/ispaneli/xemeler/tree/master/src/xemeler
Project-URL: Say Thanks!, http://saythanks.io/to/ispanelki
Project-URL: Documentation, https://github.com/ispaneli/xemeler
Keywords: xml
Classifier: Development Status :: 4 - Beta
Classifier: License :: OSI Approved :: MIT License
Classifier: Operating System :: OS Independent
Classifier: Programming Language :: Python
Classifier: Programming Language :: Python :: 3
Classifier: Programming Language :: Python :: 3 :: Only
Requires-Python: <4,>=3.8
License-File: LICENSE
